vllm_mock/__init__.py
vllm_mock/outputs.py
vllm_mock/entrypoints/__init__.py
vllm_mock/entrypoints/llm.py
vllm_mock-0.0.3.dist-info/METADATA
vllm_mock-0.0.3.dist-info/WHEEL
vllm_mock-0.0.3.dist-info/licenses/LICENSE
vllm_mock-0.0.3.dist-info/RECORD
