Metadata-Version: 2.4
Name: vllm-mock
Version: 0.0.3
Summary: Provide mock instance to test vllm without CUDA or any GPUs.
Project-URL: Homepage, https://vkehfdl1.github.io/vllm-mock/
Project-URL: Repository, https://github.com/vkehfdl1/vllm-mock
Project-URL: Documentation, https://vkehfdl1.github.io/vllm-mock/
Author-email: NomaDamas <vkehfdl1@gmail.com>
License-File: LICENSE
Keywords: python
Classifier: Intended Audience :: Developers
Classifier: Programming Language :: Python
Classifier: Programming Language :: Python :: 3
Classifier: Programming Language :: Python :: 3.10
Classifier: Programming Language :: Python :: 3.11
Classifier: Programming Language :: Python :: 3.12
Classifier: Programming Language :: Python :: 3.13
Classifier: Topic :: Software Development :: Libraries :: Python Modules
Requires-Python: <4.0,>=3.10
Requires-Dist: tqdm>=4.67.1
Requires-Dist: vllm>=0.11.0
